df4cats/__init__.py
df4cats/frames.py
df4cats/embedding/__init__.py
df4cats/embedding/generators.py
df4cats/embedding/models.py
df4cats/utils/__init__.py
df4cats/utils/maps.py
df4cats/utils/utils.py
df4cats-0.1.0.dist-info/LICENSE
df4cats-0.1.0.dist-info/METADATA
df4cats-0.1.0.dist-info/WHEEL
df4cats-0.1.0.dist-info/top_level.txt
df4cats-0.1.0.dist-info/RECORD
